compreface/__init__.py
compreface/client/__init__.py
compreface/client/add_example_of_subject.py
compreface/client/delete_example_by_id.py
compreface/client/detect_face_from_image.py
compreface/client/recognize_face_from_image.py
compreface/client/subject_client.py
compreface/client/verification_face_from_image.py
compreface/client/verify_face_from_image.py
compreface/collections/__init__.py
compreface/collections/face_collections.py
compreface/common/__init__.py
compreface/common/client.py
compreface/common/multipart_constructor.py
compreface/common/service.py
compreface/common/typed_dict.py
compreface/config/__init__.py
compreface/config/api_list.py
compreface/core/__init__.py
compreface/core/model.py
compreface/exceptions/__init__.py
compreface/exceptions/field_exception.py
compreface/service/__init__.py
compreface/service/detection_service.py
compreface/service/recognition_service.py
compreface/service/verification_service.py
compreface/use_cases/__init__.py
compreface/use_cases/add_example_of_subject.py
compreface/use_cases/add_subject.py
compreface/use_cases/delete_all_examples_of_subject_by_name.py
compreface/use_cases/delete_all_subjects.py
compreface/use_cases/delete_example_by_id.py
compreface/use_cases/delete_subject_by_name.py
compreface/use_cases/detect_face_from_image.py
compreface/use_cases/get_subjects.py
compreface/use_cases/list_of_all_saved_subjects.py
compreface/use_cases/recognize_face_from_image.py
compreface/use_cases/update_subject.py
compreface/use_cases/verification_face_from_image.py
compreface/use_cases/verifiy_face_from_images.py
compreface_sdk-0.6.0.dist-info/LICENSE
compreface_sdk-0.6.0.dist-info/METADATA
compreface_sdk-0.6.0.dist-info/WHEEL
compreface_sdk-0.6.0.dist-info/top_level.txt
compreface_sdk-0.6.0.dist-info/RECORD
