Metadata-Version: 2.1
Name: compreface-sdk
Version: 0.6.0
Summary: CompreFace Python SDK makes face recognition into your application even easier.
Home-page: https://exadel.com/solutions/compreface/
Author: Artsiom Liubymov aliubymov@exadel.com, Artsiom Khadzkou akhadzkou@exadel.com, Aliaksei Tauhen atauhen@exadel.com
Author-email: aliubymov@exadel.com, akhadzkou@exadel.com, atauhen@exadel.com
License: Apache License 2.0
Download-URL: https://github.com/exadel-inc/compreface-python-sdk/archive/refs/tags/0.6.0.tar.gz
Keywords: CompreFace,Face Recognition,Face Detection,Face Verification,Face Identification,Computer Vision,SDK
Platform: UNKNOWN
Classifier: Development Status :: 5 - Production/Stable
Classifier: Intended Audience :: Developers
Classifier: Intended Audience :: Science/Research
Classifier: Intended Audience :: Information Technology
Classifier: Topic :: Software Development
Classifier: Topic :: Software Development :: Build Tools
Classifier: Topic :: Software Development :: Libraries
Classifier: Topic :: Scientific/Engineering :: Image Recognition
Classifier: Topic :: Scientific/Engineering :: Artificial Intelligence
Classifier: License :: OSI Approved :: Apache Software License
Classifier: Programming Language :: Python :: 3
Classifier: Programming Language :: Python :: 3.7
License-File: LICENSE
